davidkhala/couchbase/__init__.py
davidkhala/couchbase/__pycache__/__init__.cpython-313.pyc
davidkhala_database-0.0.0.dist-info/METADATA
davidkhala_database-0.0.0.dist-info/WHEEL
davidkhala_database-0.0.0.dist-info/RECORD
