Metadata-Version: 2.3
Name: davidkhala.database
Version: 0.0.0
Summary: 
Author: David Liu
Author-email: david-khala@hotmail.com
Requires-Python: >=3.10
Classifier: Programming Language :: Python :: 3
Classifier: Programming Language :: Python :: 3.10
Classifier: Programming Language :: Python :: 3.11
Classifier: Programming Language :: Python :: 3.12
Classifier: Programming Language :: Python :: 3.13
Provides-Extra: couchbase
Requires-Dist: couchbase (>=0.0.0) ; extra == "couchbase"
Requires-Dist: pytest (>=0.0.0)
